ammonyte/__init__.py
ammonyte/core/__init__.py
ammonyte/core/recurrence_matrix.py
ammonyte/core/recurrence_network.py
ammonyte/core/rqa_res.py
ammonyte/core/series.py
ammonyte/core/time_embedded_series.py
ammonyte/tests/__init__.py
ammonyte/tests/test_core_recurrence_matrix.py
ammonyte/tests/test_core_recurrence_network.py
ammonyte/tests/test_core_rqa_res.py
ammonyte/tests/test_core_series.py
ammonyte/tests/test_core_time_embedded_series.py
ammonyte/tests/test_utils_parameters.py
ammonyte/utils/__init__.py
ammonyte/utils/fisher.py
ammonyte/utils/parameters.py
ammonyte/utils/plotting.py
ammonyte/utils/range_finder.py
ammonyte/utils/rm.py
ammonyte/utils/sampling.py
ammonyte/utils/synthetic_series.py
ammonyte-0.0.8.dist-info/LICENSE
ammonyte-0.0.8.dist-info/METADATA
ammonyte-0.0.8.dist-info/WHEEL
ammonyte-0.0.8.dist-info/top_level.txt
ammonyte-0.0.8.dist-info/RECORD
