Metadata-Version: 2.1
Name: ammonyte
Version: 0.0.8
Summary: A Python package for nonlinear paleoclimate data analysis
Home-page: https://github.com/alexkjames/Ammonyte
Author: Alexander James
Author-email: akjames@usc.edu
License: GPL-3.0 License
Keywords: Paleoclimate, Data Analysis, Nonlinear
Requires-Python: >=3.8.0
License-File: LICENSE
Requires-Dist: pyleoclim (>=0.7.0)
Requires-Dist: scipy (>=1.7.1)
Requires-Dist: numpy (>=1.21.5)
Requires-Dist: PyRQA (>=8.0.0)
Requires-Dist: scikit-learn (>=1.2.1)
